codedepot_depot-0.0.22.dist-info/METADATA
codedepot_depot-0.0.22.dist-info/WHEEL
codedepot_depot-0.0.22.dist-info/entry_points.txt
depot/__init__.py
depot/api.py
depot/cluster_spec.py
depot/config.py
depot/jobfile.py
depot/main.py
depot/provider_spec.py
test/__init__.py
test/resources/cluster_test.yaml
test/resources/config.json
test/resources/local_cred.json
test/resources/provider_test.yaml
test/test_client.py
test/test_provider.py
test/utils.py
codedepot_depot-0.0.22.dist-info/RECORD
