Metadata-Version: 2.1
Name: codedepot-depot
Version: 0.0.22
Summary: Job launch support for Git AI
Author-Email: CodeDepot <contact@codedepot.ai>
Classifier: License :: OSI Approved :: MIT License
Classifier: Operating System :: OS Independent
Classifier: Programming Language :: Python :: 3
Project-URL: Homepage, https://github.com/codedepotai/git-ai
Requires-Python: >=3.10
Requires-Dist: depot-api
Requires-Dist: prettytable
Requires-Dist: prompt-toolkit
Requires-Dist: py
Requires-Dist: pyaml
Requires-Dist: pydantic
Requires-Dist: pygit2
Requires-Dist: requests
Requires-Dist: depot_api
Requires-Dist: codedepot-git-ai>=0.0.20
Requires-Dist: depot-api>=1.0.3
Requires-Dist: depot-api>=1.0.4
Requires-Dist: codedepot-git-ai>=0.0.24
Requires-Dist: inquirer
Requires-Dist: depot-api>=1.0.5
Requires-Dist: depot-api>=1.0.6
Requires-Dist: depot-api>=1.0.7
Requires-Dist: depot-api>=1.0.8
Requires-Dist: codedepot-git-ai>=0.0.25
Requires-Dist: depot-api>=1.0.9
